LICENSE
MANIFEST.in
README.md
quicktest.py
settings_test.py
setup.py
django_twitter_api.egg-info/PKG-INFO
django_twitter_api.egg-info/SOURCES.txt
django_twitter_api.egg-info/dependency_links.txt
django_twitter_api.egg-info/not-zip-safe
django_twitter_api.egg-info/requires.txt
django_twitter_api.egg-info/top_level.txt
twitter_api/__init__.py
twitter_api/__init__.pyc
twitter_api/admin.py
twitter_api/admin.pyc
twitter_api/api.py
twitter_api/api.pyc
twitter_api/decorators.py
twitter_api/decorators.pyc
twitter_api/factories.py
twitter_api/factories.pyc
twitter_api/fields.py
twitter_api/fields.pyc
twitter_api/models.py
twitter_api/models.pyc
twitter_api/parser.py
twitter_api/parser.pyc
twitter_api/tests.py
twitter_api/tests.pyc
twitter_api/migrations/0001_initial.py
twitter_api/migrations/0001_initial.pyc
twitter_api/migrations/__init__.py
twitter_api/migrations/__init__.pyc
twitter_api/sql/status.postgresql_psycopg2.sql
twitter_api/sql/user.postgresql_psycopg2.sql